{
    "JsonFileType": "Level",
    "SceneActor": [
        {
            "scene_actor_prefab_type_key": "BGM_Manager",
            "path_key": "Resource/Json/PrefabActor/BGM_Manager.json",
            "object_type_key": "",
            "scene_actor_name_key": "BGM_Manager",
            "active": true,
            "ComponentType": "AudioComponent",
            "audioMap": [
                {
                    "Path": "Resource\\Audio\\BGM_InGame.wav",
                    "Volume": 0.699998,
                    "Loop": true,
                    "State": "IDLE"
                }
            ]
        },
        {
            "scene_actor_prefab_type_key": "Surtur",
            "path_key": "Resource/Json/PrefabActor/Surtur.json",
            "object_type_key": "Player",
            "scene_actor_name_key": "Surtur",
            "active": true,
            "m_Pos.x": 24,
            "m_Pos.y": -50,
            "m_Rotate": 0.0,
            "m_Scale.x": 3.0,
            "m_Scale.y": 3.0,
            "m_aabbScale.x": 0.2,
            "m_aabbScale.y": 0.33,
            "m_offset.x": 0.0,
            "m_offset.y": 0.0,
            "Orthogonal_Camera": false,
            "Layer": 12,
            "m_direction.x": 0.0,
            "m_direction.y": 0.0,
            "m_startTime": 0.0,
            "m_duration": 0.0,
            "m_modA": 0.0,
            "m_modB": 0.0,
            "ComponentType": "AudioComponent",
            "audioMap": [
                {
                    "Path": "Resource/Audio/PlayerSlash.wav",
                    "Volume": 0.699998,
                    "Loop": false,
                    "State": "ATTACK1"
                },
                {
                    "Path": "Resource/Audio/PlayerSlash.wav",
                    "Volume": 0.699998,
                    "Loop": false,
                    "State": "ATTACK2"
                },
                {
                    "Path": "Resource/Audio/PlayerSlash.wav",
                    "Volume": 0.699998,
                    "Loop": false,
                    "State": "ATTACK3"
                },
                {
                    "Path": "Resource/Audio/PlayerDash.wav",
                    "Volume": 0.5,
                    "Loop": false,
                    "State": "DASH"
                },
                {
                    "Path": "Resource/Audio/PlayerDeath.wav",
                    "Volume": 1.0,
                    "Loop": false,
                    "State": "DIE"
                },
                {
                    "Path": "Resource/Audio/PlayerDoubleJump.wav",
                    "Volume": 1.0,
                    "Loop": false,
                    "State": "DOUBLEJUMP"
                },
                {
                    "Path": "NO AUDIO",
                    "Volume": 0.0,
                    "Loop": false,
                    "State": "FALL"
                },
                {
                    "Path": "Resource/Audio/ValkyrieSpearHit.wav",
                    "Volume": 1.0,
                    "Loop": false,
                    "State": "HURT"
                },
                {
                    "Path": "NO AUDIO",
                    "Volume": 1.0,
                    "Loop": false,
                    "State": "IDLE"
                },
                {
                    "Path": "Resource/Audio/PlayerJump.wav",
                    "Volume": 0.3,
                    "Loop": false,
                    "State": "JUMP"
                },
                {
                    "Path": "Resource/Audio/PlayerSlash.wav",
                    "Volume": 0.699998,
                    "Loop": false,
                    "State": "JUMPATTACK"
                },
                {
                    "Path": "NO AUDIO",
                    "Volume": 1.0,
                    "Loop": false,
                    "State": "LAND"
                },
                {
                    "Path": "Resource/Audio/SawCollision.wav",
                    "Volume": 0.5,
                    "Loop": false,
                    "State": "RESPAWN"
                },
                {
                    "Path": "Resource/Audio/PlayerWalk.wav",
                    "Volume": 0.5,
                    "Loop": true,
                    "State": "WALK"
                }
            ],
            "cam_pos_x": 48.529998,
            "cam_pos_y": -89.999992,
            "cam_pos_z": 6.000009,
            "cam_front_x": 0.0,
            "cam_front_y": 0.0,
            "cam_front_z": -1.0,
            "cam_up_x": 0.0,
            "cam_up_y": 1.0,
            "cam_up_z": 0.0,
            "cam_offset_pos_x": 0.0,
            "cam_offset_pos_y": 1.0,
            "child_scene_actor_container": [
                {
                    "scene_actor_prefab_type_key": "PlayerDashHitbox",
                    "path_key": "Resource/Json/PrefabActor/PlayerDashHitbox.json",
                    "object_type_key": "PlayerHitbox",
                    "scene_actor_name_key": "PlayerDashHitbox",
                    "active": false,
                    "m_Pos.x": 10.384143,
                    "m_Pos.y": -15.504999,
                    "m_Rotate": 0.0,
                    "m_Scale.x": 0.5,
                    "m_Scale.y": 1.0,
                    "Orthogonal_Camera": false,
                    "Layer": 12,
                    "m_aabbScale.x": 1.0,
                    "m_aabbScale.y": 1.0,
                    "m_offset.x": -0.6,
                    "m_offset.y": 0.0,
                    "m_direction.x": 0.0,
                    "m_direction.y": 0.0,
                    "m_startTime": 0.0,
                    "m_duration": 0.0,
                    "m_modA": 0.0,
                    "m_modB": 0.0,
                    "scene_actor_tagging": [
                        {
                            "scene_actor_tagging_key": "scene_actor_prefab_type_key",
                            "scene_actor_tagging_value": "PlayerDashHitbox"
                        }
                    ]
                },
                {
                    "scene_actor_prefab_type_key": "SurtrSummonPunch",
                    "path_key": "Resource/Json/PrefabActor/SurtrSummonPunch.json",
                    "object_type_key": "Background",
                    "scene_actor_name_key": "SurtrSummonPunch",
                    "active": false,
                    "m_Pos.x": 9.784143,
                    "m_Pos.y": -15.504999,
                    "m_Rotate": 0.0,
                    "m_Scale.x": 8.0,
                    "m_Scale.y": 4.0,
                    "Orthogonal_Camera": false,
                    "Layer": 12,
                    "m_aabbScale.x": 1.0,
                    "m_aabbScale.y": 1.0,
                    "m_offset.x": 0.0,
                    "m_offset.y": 0.0,
                    "scene_actor_tagging": [
                        {
                            "scene_actor_tagging_key": "scene_actor_prefab_type_key",
                            "scene_actor_tagging_value": "SurtrSummonPunch"
                        }
                    ]
                },
                {
                    "scene_actor_prefab_type_key": "Black Screen",
                    "path_key": "Resource/Json/PrefabActor/Black Screen.json",
                    "object_type_key": "Background",
                    "scene_actor_name_key": "Black Screen",
                    "active": true,
                    "m_Pos.x": 640.0,
                    "m_Pos.y": 400.0,
                    "m_Rotate": 0.0,
                    "m_Scale.x": 0.0,
                    "m_Scale.y": 0.0,
                    "Orthogonal_Camera": true,
                    "Layer": 13,
                    "scene_actor_tagging": [
                        {
                            "scene_actor_tagging_key": "scene_actor_prefab_type_key",
                            "scene_actor_tagging_value": "Black Screen"
                        }
                    ]
                },
                {
                    "scene_actor_prefab_type_key": "PlayerHitbox",
                    "path_key": "Resource/Json/PrefabActor/PlayerHitbox.json",
                    "object_type_key": "PlayerHitbox",
                    "scene_actor_name_key": "PlayerChargeHitbox",
                    "active": false,
                    "m_Pos.x": 11.684142,
                    "m_Pos.y": -15.504999,
                    "m_Rotate": 0.0,
                    "m_Scale.x": 1.0,
                    "m_Scale.y": 1.0,
                    "Orthogonal_Camera": false,
                    "Layer": 12,
                    "m_aabbScale.x": 3.0,
                    "m_aabbScale.y": 2.0,
                    "m_offset.x": -1.899999,
                    "m_offset.y": 0.0,
                    "m_direction.x": 0.0,
                    "m_direction.y": 0.0,
                    "m_startTime": 0.0,
                    "m_duration": 0.0,
                    "m_modA": 0.0,
                    "m_modB": 0.0,
                    "scene_actor_tagging": [
                        {
                            "scene_actor_tagging_key": "scene_actor_prefab_type_key",
                            "scene_actor_tagging_value": "PlayerHitbox"
                        }
                    ]
                },
                {
                    "scene_actor_prefab_type_key": "PlayerHitbox",
                    "path_key": "Resource/Json/PrefabActor/PlayerHitbox.json",
                    "object_type_key": "PlayerHitbox",
                    "scene_actor_name_key": "PlayerGroundPoundHitbox1",
                    "active": false,
                    "m_Pos.x": 9.784143,
                    "m_Pos.y": -15.504999,
                    "m_Rotate": 0.0,
                    "m_Scale.x": 1.0,
                    "m_Scale.y": 1.0,
                    "Orthogonal_Camera": false,
                    "Layer": 12,
                    "m_aabbScale.x": 2.0,
                    "m_aabbScale.y": 2.0,
                    "m_offset.x": 0.0,
                    "m_offset.y": 0.0,
                    "m_direction.x": 0.0,
                    "m_direction.y": 0.0,
                    "m_startTime": 0.0,
                    "m_duration": 0.0,
                    "m_modA": 0.0,
                    "m_modB": 0.0,
                    "scene_actor_tagging": [
                        {
                            "scene_actor_tagging_key": "scene_actor_prefab_type_key",
                            "scene_actor_tagging_value": "PlayerHitbox"
                        }
                    ]
                },
                {
                    "scene_actor_prefab_type_key": "PlayerHitbox",
                    "path_key": "Resource/Json/PrefabActor/PlayerHitbox.json",
                    "object_type_key": "PlayerHitbox",
                    "scene_actor_name_key": "PlayerGroundPoundHitbox2",
                    "active": false,
                    "m_Pos.x": 9.784143,
                    "m_Pos.y": -15.004999,
                    "m_Rotate": 0.0,
                    "m_Scale.x": 1.0,
                    "m_Scale.y": 1.0,
                    "Orthogonal_Camera": false,
                    "Layer": 12,
                    "m_aabbScale.x": 6.0,
                    "m_aabbScale.y": 3.0,
                    "m_offset.x": 0.0,
                    "m_offset.y": 0.5,
                    "m_direction.x": 0.0,
                    "m_direction.y": 0.0,
                    "m_startTime": 0.0,
                    "m_duration": 0.0,
                    "m_modA": 0.0,
                    "m_modB": 0.0,
                    "scene_actor_tagging": [
                        {
                            "scene_actor_tagging_key": "scene_actor_prefab_type_key",
                            "scene_actor_tagging_value": "PlayerHitbox"
                        }
                    ]
                },
                {
                    "scene_actor_prefab_type_key": "PlayerHitbox",
                    "path_key": "Resource/Json/PrefabActor/PlayerHitbox.json",
                    "object_type_key": "PlayerHitbox",
                    "scene_actor_name_key": "BigPunchHitbox",
                    "active": false,
                    "m_Pos.x": 11.784143,
                    "m_Pos.y": -15.504999,
                    "m_Rotate": 0.0,
                    "m_Scale.x": 1.0,
                    "m_Scale.y": 1.0,
                    "Orthogonal_Camera": false,
                    "Layer": 12,
                    "m_aabbScale.x": 1.0,
                    "m_aabbScale.y": 1.0,
                    "m_offset.x": -2.0,
                    "m_offset.y": 0.0,
                    "m_direction.x": 0.0,
                    "m_direction.y": 0.0,
                    "m_startTime": 0.0,
                    "m_duration": 0.0,
                    "m_modA": 0.0,
                    "m_modB": 0.0,
                    "scene_actor_tagging": [
                        {
                            "scene_actor_tagging_key": "scene_actor_prefab_type_key",
                            "scene_actor_tagging_value": "PlayerHitbox"
                        }
                    ]
                },
                {
                    "scene_actor_prefab_type_key": "PlayerHitbox",
                    "path_key": "Resource/Json/PrefabActor/PlayerHitbox.json",
                    "object_type_key": "PlayerHitbox",
                    "scene_actor_name_key": "PlayerHitbox",
                    "active": false,
                    "m_Pos.x": 10.984143,
                    "m_Pos.y": -15.504999,
                    "m_Rotate": 0.0,
                    "m_Scale.x": 1.399999,
                    "m_Scale.y": 1.2,
                    "Orthogonal_Camera": false,
                    "Layer": 12,
                    "m_aabbScale.x": 1.0,
                    "m_aabbScale.y": 1.0,
                    "m_offset.x": -1.2,
                    "m_offset.y": 0.0,
                    "m_direction.x": 0.0,
                    "m_direction.y": 0.0,
                    "m_startTime": 0.0,
                    "m_duration": 0.0,
                    "m_modA": 0.0,
                    "m_modB": 0.0,
                    "scene_actor_tagging": [
                        {
                            "scene_actor_tagging_key": "scene_actor_prefab_type_key",
                            "scene_actor_tagging_value": "PlayerHitbox"
                        }
                    ]
                },
                {
                    "scene_actor_prefab_type_key": "PlayerHitbox",
                    "path_key": "Resource/Json/PrefabActor/PlayerHitbox.json",
                    "object_type_key": "PlayerHitbox",
                    "scene_actor_name_key": "PlayerHitbox(2)",
                    "active": false,
                    "m_Pos.x": 10.484141,
                    "m_Pos.y": -15.504999,
                    "m_Rotate": 0.0,
                    "m_Scale.x": 1.0,
                    "m_Scale.y": 1.2,
                    "Orthogonal_Camera": false,
                    "Layer": 12,
                    "m_aabbScale.x": 1.0,
                    "m_aabbScale.y": 1.0,
                    "m_offset.x": -0.699998,
                    "m_offset.y": 0.0,
                    "m_direction.x": 0.0,
                    "m_direction.y": 0.0,
                    "m_startTime": 0.0,
                    "m_duration": 0.0,
                    "m_modA": 0.0,
                    "m_modB": 0.0,
                    "scene_actor_tagging": [
                        {
                            "scene_actor_tagging_key": "scene_actor_prefab_type_key",
                            "scene_actor_tagging_value": "PlayerHitbox"
                        }
                    ]
                },
                {
                    "scene_actor_prefab_type_key": "PlayerDashFX",
                    "path_key": "Resource/Json/PrefabActor/PlayerDashFX.json",
                    "object_type_key": "Custom",
                    "scene_actor_name_key": "PlayerDashFX",
                    "active": false,
                    "m_Pos.x": 9.084145,
                    "m_Pos.y": -15.454998,
                    "m_Rotate": 0.0,
                    "m_Scale.x": -1.0,
                    "m_Scale.y": 1.0,
                    "Orthogonal_Camera": false,
                    "Layer": 12,
                    "m_aabbScale.x": 1.0,
                    "m_aabbScale.y": 1.0,
                    "m_offset.x": 0.699998,
                    "m_offset.y": 0.05,
                    "scene_actor_tagging": [
                        {
                            "scene_actor_tagging_key": "scene_actor_prefab_type_key",
                            "scene_actor_tagging_value": "PlayerDashFX"
                        }
                    ]
                },
                {
                    "scene_actor_prefab_type_key": "PlayerDoubleJumpFX",
                    "path_key": "Resource/Json/PrefabActor/PlayerDoubleJumpFX.json",
                    "object_type_key": "Custom",
                    "scene_actor_name_key": "PlayerDoubleJumpFX",
                    "active": false,
                    "m_Pos.x": 9.784143,
                    "m_Pos.y": -16.104999,
                    "m_Rotate": 0.0,
                    "m_Scale.x": 2.0,
                    "m_Scale.y": 2.0,
                    "Orthogonal_Camera": false,
                    "Layer": 12,
                    "m_aabbScale.x": 1.0,
                    "m_aabbScale.y": 1.0,
                    "m_offset.x": 0.0,
                    "m_offset.y": -0.6,
                    "scene_actor_tagging": [
                        {
                            "scene_actor_tagging_key": "scene_actor_prefab_type_key",
                            "scene_actor_tagging_value": "PlayerDoubleJumpFX"
                        }
                    ]
                },
                {
                    "scene_actor_prefab_type_key": "PlayerDashDustFX",
                    "path_key": "Resource/Json/PrefabActor/PlayerDashDustFX.json",
                    "object_type_key": "Custom",
                    "scene_actor_name_key": "PlayerDashDustFX",
                    "active": false,
                    "m_Pos.x": 9.084145,
                    "m_Pos.y": -15.404998,
                    "m_Rotate": 0.0,
                    "m_Scale.x": -1.0,
                    "m_Scale.y": 1.0,
                    "Orthogonal_Camera": false,
                    "Layer": 12,
                    "m_aabbScale.x": 1.0,
                    "m_aabbScale.y": 1.0,
                    "m_offset.x": 0.699998,
                    "m_offset.y": 0.1,
                    "scene_actor_tagging": [
                        {
                            "scene_actor_tagging_key": "scene_actor_prefab_type_key",
                            "scene_actor_tagging_value": "PlayerDashDustFX"
                        }
                    ]
                },
                {
                    "scene_actor_prefab_type_key": "PlayerDamageFX",
                    "path_key": "Resource/Json/PrefabActor/PlayerDamageFX.json",
                    "object_type_key": "Custom",
                    "scene_actor_name_key": "PlayerDamageFX",
                    "active": false,
                    "m_Pos.x": 9.784143,
                    "m_Pos.y": -15.504999,
                    "m_Rotate": 0.0,
                    "m_Scale.x": 1.5,
                    "m_Scale.y": 1.5,
                    "Orthogonal_Camera": false,
                    "Layer": 12,
                    "m_aabbScale.x": 1.0,
                    "m_aabbScale.y": 1.0,
                    "m_offset.x": 0.0,
                    "m_offset.y": 0.0,
                    "scene_actor_tagging": [
                        {
                            "scene_actor_tagging_key": "scene_actor_prefab_type_key",
                            "scene_actor_tagging_value": "PlayerDamageFX"
                        }
                    ]
                },
                {
                    "scene_actor_prefab_type_key": "LevelEndWord_Level",
                    "path_key": "Resource/Json/PrefabActor/LevelEndWord_Level.json",
                    "object_type_key": "Custom",
                    "scene_actor_name_key": "LevelEndWord_Level",
                    "active": false,
                    "m_Pos.x": 10.784143,
                    "m_Pos.y": -14.754999,
                    "m_Rotate": 0.0,
                    "m_Scale.x": 2.0,
                    "m_Scale.y": 1.0,
                    "Orthogonal_Camera": false,
                    "Layer": 12,
                    "m_aabbScale.x": 1.0,
                    "m_aabbScale.y": 1.0,
                    "m_offset.x": -1.0,
                    "m_offset.y": 0.75,
                    "scene_actor_tagging": [
                        {
                            "scene_actor_tagging_key": "scene_actor_prefab_type_key",
                            "scene_actor_tagging_value": "LevelEndWord_Level"
                        }
                    ]
                },
                {
                    "scene_actor_prefab_type_key": "LevelEndWord_Clear",
                    "path_key": "Resource/Json/PrefabActor/LevelEndWord_Clear.json",
                    "object_type_key": "Custom",
                    "scene_actor_name_key": "LevelEndWord_Clear",
                    "active": false,
                    "m_Pos.x": 8.784143,
                    "m_Pos.y": -14.754999,
                    "m_Rotate": 0.0,
                    "m_Scale.x": 1.0,
                    "m_Scale.y": 1.0,
                    "Orthogonal_Camera": false,
                    "Layer": 12,
                    "m_aabbScale.x": 1.0,
                    "m_aabbScale.y": 1.0,
                    "m_offset.x": 1.0,
                    "m_offset.y": 0.75,
                    "scene_actor_tagging": [
                        {
                            "scene_actor_tagging_key": "scene_actor_prefab_type_key",
                            "scene_actor_tagging_value": "LevelEndWord_Clear"
                        }
                    ]
                },
                {
                    "scene_actor_prefab_type_key": "LevelEndWord_LevelClear",
                    "path_key": "Resource/Json/PrefabActor/LevelEndWord_LevelClear.json",
                    "object_type_key": "Custom",
                    "scene_actor_name_key": "LevelEndWord_LevelClear",
                    "active": false,
                    "m_Pos.x": 9.784143,
                    "m_Pos.y": -17.504999,
                    "m_Rotate": 0.0,
                    "m_Scale.x": 0.0,
                    "m_Scale.y": 0.0,
                    "Orthogonal_Camera": false,
                    "Layer": 12,
                    "m_aabbScale.x": 1.0,
                    "m_aabbScale.y": 1.0,
                    "m_offset.x": 0.0,
                    "m_offset.y": -2.0,
                    "scene_actor_tagging": [
                        {
                            "scene_actor_tagging_key": "scene_actor_prefab_type_key",
                            "scene_actor_tagging_value": "LevelEndWord_LevelClear"
                        }
                    ]
                },
                {
                    "scene_actor_prefab_type_key": "PlayerInvulnFX",
                    "path_key": "Resource/Json/PrefabActor/PlayerInvulnFX.json",
                    "object_type_key": "Custom",
                    "scene_actor_name_key": "PlayerInvulnFX",
                    "active": false,
                    "m_Pos.x": 9.784143,
                    "m_Pos.y": -15.504999,
                    "m_Rotate": 0.0,
                    "m_Scale.x": 1.5,
                    "m_Scale.y": 1.0,
                    "Orthogonal_Camera": false,
                    "Layer": 12,
                    "m_aabbScale.x": 1.0,
                    "m_aabbScale.y": 1.0,
                    "m_offset.x": 0.0,
                    "m_offset.y": 0.0,
                    "scene_actor_tagging": [
                        {
                            "scene_actor_tagging_key": "scene_actor_prefab_type_key",
                            "scene_actor_tagging_value": "PlayerInvulnFX"
                        }
                    ]
                }
            ]
        },
        {
            "scene_actor_prefab_type_key": "Level03_004",
            "path_key": "Resource/Json/PrefabActor/Level04_004.json",
            "object_type_key": "",
            "scene_actor_name_key": "Level04_004",
            "active": true,
            "m_Pos.x": 16.0,
            "m_Pos.y": -48.0,
            "m_Rotate": 0.0,
            "m_Scale.x": 32.0,
            "m_Scale.y": 32.0,
            "Orthogonal_Camera": false,
            "Layer": 1,
            "m_direction.x": 0.0,
            "m_direction.y": 0.0,
            "m_startTime": 0.0,
            "m_duration": 0.0,
            "m_modA": 0.1,
            "m_modB": 0.0
        },
        {
            "scene_actor_prefab_type_key": "Level03_005",
            "path_key": "Resource/Json/PrefabActor/Level04_005.json",
            "object_type_key": "",
            "scene_actor_name_key": "Level04_005",
            "active": true,
            "m_Pos.x": 48.0,
            "m_Pos.y": -48.0,
            "m_Rotate": 0.0,
            "m_Scale.x": 32.0,
            "m_Scale.y": 32.0,
            "Orthogonal_Camera": false,
            "Layer": 1,
            "m_direction.x": 0.0,
            "m_direction.y": 0.0,
            "m_startTime": 0.0,
            "m_duration": 0.0,
            "m_modA": 0.1,
            "m_modB": 0.0
        },
        {
            "scene_actor_prefab_type_key": "Level03_006",
            "path_key": "Resource/Json/PrefabActor/Level04_006.json",
            "object_type_key": "",
            "scene_actor_name_key": "Level04_006",
            "active": true,
            "m_Pos.x": 80.0,
            "m_Pos.y": -48.0,
            "m_Rotate": 0.0,
            "m_Scale.x": 32.0,
            "m_Scale.y": 32.0,
            "Orthogonal_Camera": false,
            "Layer": 1,
            "m_direction.x": 0.0,
            "m_direction.y": 0.0,
            "m_startTime": 0.0,
            "m_duration": 0.0,
            "m_modA": 0.1,
            "m_modB": 0.0
        },
        {
            "scene_actor_prefab_type_key": "ColliderBox",
            "path_key": "Resource/Json/PrefabActor/ColliderBox.json",
            "object_type_key": "ColliderBox",
            "scene_actor_name_key": "ColliderBox_01",
            "active": true,
            "m_Pos.x": 13,
            "m_Pos.y": -48,
            "m_Rotate": 0.0,
            "m_Scale.x": 6.0,
            "m_Scale.y": 24.0,
            "m_aabbScale.x": 1.0,
            "m_aabbScale.y": 1.0,
            "m_offset.x": 0.0,
            "m_offset.y": 0.0,
            "Orthogonal_Camera": false,
            "Layer": 20,
            "m_direction.x": 0.0,
            "m_direction.y": 0.0,
            "m_startTime": 0.0,
            "m_duration": 0.0,
            "m_modA": 0.0,
            "m_modB": 0.0
        },
        {
            "scene_actor_prefab_type_key": "ColliderBox",
            "path_key": "Resource/Json/PrefabActor/ColliderBox.json",
            "object_type_key": "ColliderBox",
            "scene_actor_name_key": "ColliderBox_02",
            "active": true,
            "m_Pos.x": 25.5,
            "m_Pos.y": -41,
            "m_Rotate": 0.0,
            "m_Scale.x": 19.0,
            "m_Scale.y": 10.0,
            "m_aabbScale.x": 1.0,
            "m_aabbScale.y": 1.0,
            "m_offset.x": 0.0,
            "m_offset.y": 0.0,
            "Orthogonal_Camera": false,
            "Layer": 20,
            "m_direction.x": 0.0,
            "m_direction.y": 0.0,
            "m_startTime": 0.0,
            "m_duration": 0.0,
            "m_modA": 0.0,
            "m_modB": 0.0
        },
        {
            "scene_actor_prefab_type_key": "ColliderBox",
            "path_key": "Resource/Json/PrefabActor/ColliderBox.json",
            "object_type_key": "ColliderBox",
            "scene_actor_name_key": "ColliderBox_03",
            "active": true,
            "m_Pos.x": 48,
            "m_Pos.y": -39,
            "m_Rotate": 0.0,
            "m_Scale.x": 26,
            "m_Scale.y": 6.0,
            "m_aabbScale.x": 1.0,
            "m_aabbScale.y": 1.0,
            "m_offset.x": 0.0,
            "m_offset.y": 0.0,
            "Orthogonal_Camera": false,
            "Layer": 20,
            "m_direction.x": 0.0,
            "m_direction.y": 0.0,
            "m_startTime": 0.0,
            "m_duration": 0.0,
            "m_modA": 0.0,
            "m_modB": 0.0
        },
        {
            "scene_actor_prefab_type_key": "ColliderBox",
            "path_key": "Resource/Json/PrefabActor/ColliderBox.json",
            "object_type_key": "ColliderBox",
            "scene_actor_name_key": "ColliderBox_04",
            "active": true,
            "m_Pos.x": 70.5,
            "m_Pos.y": -41,
            "m_Rotate": 0.0,
            "m_Scale.x": 19.0,
            "m_Scale.y": 10.0,
            "m_aabbScale.x": 1.0,
            "m_aabbScale.y": 1.0,
            "m_offset.x": 0.0,
            "m_offset.y": 0.0,
            "Orthogonal_Camera": false,
            "Layer": 20,
            "m_direction.x": 0.0,
            "m_direction.y": 0.0,
            "m_startTime": 0.0,
            "m_duration": 0.0,
            "m_modA": 0.0,
            "m_modB": 0.0
        },
        {
            "scene_actor_prefab_type_key": "ColliderBox",
            "path_key": "Resource/Json/PrefabActor/ColliderBox.json",
            "object_type_key": "ColliderBox",
            "scene_actor_name_key": "ColliderBox_05",
            "active": true,
            "m_Pos.x": 83,
            "m_Pos.y": -48,
            "m_Rotate": 0.0,
            "m_Scale.x": 6.0,
            "m_Scale.y": 24.0,
            "m_aabbScale.x": 1.0,
            "m_aabbScale.y": 1.0,
            "m_offset.x": 0.0,
            "m_offset.y": 0.0,
            "Orthogonal_Camera": false,
            "Layer": 20,
            "m_direction.x": 0.0,
            "m_direction.y": 0.0,
            "m_startTime": 0.0,
            "m_duration": 0.0,
            "m_modA": 0.0,
            "m_modB": 0.0
        },
        {
            "scene_actor_prefab_type_key": "ColliderBox",
            "path_key": "Resource/Json/PrefabActor/ColliderBox.json",
            "object_type_key": "ColliderBox",
            "scene_actor_name_key": "ColliderBox_06",
            "active": true,
            "m_Pos.x": 25.5,
            "m_Pos.y": -55,
            "m_Rotate": 0.0,
            "m_Scale.x": 19.0,
            "m_Scale.y": 10.0,
            "m_aabbScale.x": 1.0,
            "m_aabbScale.y": 1.0,
            "m_offset.x": 0.0,
            "m_offset.y": 0.0,
            "Orthogonal_Camera": false,
            "Layer": 20,
            "m_direction.x": 0.0,
            "m_direction.y": 0.0,
            "m_startTime": 0.0,
            "m_duration": 0.0,
            "m_modA": 0.0,
            "m_modB": 0.0
        },
        {
            "scene_actor_prefab_type_key": "ColliderBox",
            "path_key": "Resource/Json/PrefabActor/ColliderBox.json",
            "object_type_key": "ColliderBox",
            "scene_actor_name_key": "ColliderBox_07",
            "active": true,
            "m_Pos.x": 48,
            "m_Pos.y": -57,
            "m_Rotate": 0.0,
            "m_Scale.x": 26.0,
            "m_Scale.y": 6.0,
            "m_aabbScale.x": 1.0,
            "m_aabbScale.y": 1.0,
            "m_offset.x": 0.0,
            "m_offset.y": 0.0,
            "Orthogonal_Camera": false,
            "Layer": 20,
            "m_direction.x": 0.0,
            "m_direction.y": 0.0,
            "m_startTime": 0.0,
            "m_duration": 0.0,
            "m_modA": 0.0,
            "m_modB": 0.0
        },
        {
            "scene_actor_prefab_type_key": "ColliderBox",
            "path_key": "Resource/Json/PrefabActor/ColliderBox.json",
            "object_type_key": "ColliderBox",
            "scene_actor_name_key": "ColliderBox_08",
            "active": true,
            "m_Pos.x": 48,
            "m_Pos.y": -52.5,
            "m_Rotate": 0.0,
            "m_Scale.x": 18.0,
            "m_Scale.y": 3.0,
            "m_aabbScale.x": 1.0,
            "m_aabbScale.y": 1.0,
            "m_offset.x": 0.0,
            "m_offset.y": 0.0,
            "Orthogonal_Camera": false,
            "Layer": 20,
            "m_direction.x": 0.0,
            "m_direction.y": 0.0,
            "m_startTime": 0.0,
            "m_duration": 0.0,
            "m_modA": 0.0,
            "m_modB": 0.0
        },
        {
            "scene_actor_prefab_type_key": "ColliderBox",
            "path_key": "Resource/Json/PrefabActor/ColliderBox.json",
            "object_type_key": "ColliderBox",
            "scene_actor_name_key": "ColliderBox_09",
            "active": true,
            "m_Pos.x": 48,
            "m_Pos.y": -50.5,
            "m_Rotate": 0.0,
            "m_Scale.x": 8.0,
            "m_Scale.y": 1.0,
            "m_aabbScale.x": 1.0,
            "m_aabbScale.y": 1.0,
            "m_offset.x": 0.0,
            "m_offset.y": 0.0,
            "Orthogonal_Camera": false,
            "Layer": 20,
            "m_direction.x": 0.0,
            "m_direction.y": 0.0,
            "m_startTime": 0.0,
            "m_duration": 0.0,
            "m_modA": 0.0,
            "m_modB": 0.0
        },
        {
            "scene_actor_prefab_type_key": "ColliderBox",
            "path_key": "Resource/Json/PrefabActor/ColliderBox.json",
            "object_type_key": "ColliderBox",
            "scene_actor_name_key": "ColliderBox_10",
            "active": true,
            "m_Pos.x": 70.5,
            "m_Pos.y": -55,
            "m_Rotate": 0.0,
            "m_Scale.x": 19.0,
            "m_Scale.y": 10.0,
            "m_aabbScale.x": 1.0,
            "m_aabbScale.y": 1.0,
            "m_offset.x": 0.0,
            "m_offset.y": 0.0,
            "Orthogonal_Camera": false,
            "Layer": 20,
            "m_direction.x": 0.0,
            "m_direction.y": 0.0,
            "m_startTime": 0.0,
            "m_duration": 0.0,
            "m_modA": 0.0,
            "m_modB": 0.0
        },
        {
            "scene_actor_prefab_type_key": "SpikeColliderBox",
            "path_key": "Resource/Json/PrefabActor/SpikeColliderBox.json",
            "object_type_key": "SpikeColliderBox",
            "scene_actor_name_key": "SpikeColliderBox_01",
            "active": true,
            "m_Pos.x": 37,
            "m_Pos.y": -53.5,
            "m_Rotate": 0.0,
            "m_Scale.x": 4.0,
            "m_Scale.y": 0.6,
            "m_aabbScale.x": 1.0,
            "m_aabbScale.y": 1.0,
            "m_offset.x": 0.0,
            "m_offset.y": 0.0,
            "Orthogonal_Camera": false,
            "Layer": 20,
            "m_direction.x": 0.0,
            "m_direction.y": 0.0,
            "m_startTime": 0.0,
            "m_duration": 0.0,
            "m_modA": 0.0,
            "m_modB": 0.0
        },
        {
            "scene_actor_prefab_type_key": "SpikeColliderBox",
            "path_key": "Resource/Json/PrefabActor/SpikeColliderBox.json",
            "object_type_key": "SpikeColliderBox",
            "scene_actor_name_key": "SpikeColliderBox_02",
            "active": true,
            "m_Pos.x": 59,
            "m_Pos.y": -53.5,
            "m_Rotate": 0.0,
            "m_Scale.x": 4.0,
            "m_Scale.y": 0.6,
            "m_aabbScale.x": 1.0,
            "m_aabbScale.y": 1.0,
            "m_offset.x": 0.0,
            "m_offset.y": 0.0,
            "Orthogonal_Camera": false,
            "Layer": 20,
            "m_direction.x": 0.0,
            "m_direction.y": 0.0,
            "m_startTime": 0.0,
            "m_duration": 0.0,
            "m_modA": 0.0,
            "m_modB": 0.0
        }
    ],
    "LevelCoordinate": {
        "global_coordinate_min_x": 0.0,
        "global_coordinate_max_x": 96.0,
        "global_coordinate_min_y": -96.0,
        "global_coordinate_max_y": 0.0
    }
}